kal_utils/__init__.py
kal_utils/env.py
kal_utils/handle_response.py
kal_utils/helper.py
kal_utils/kal_utils.py
kal_utils/mongodb.py
kal_utils/requests.py
kal_utils/sorts.py
kal_utils/time_zone.py
kal_utils/event_messaging/__init__.py
kal_utils/event_messaging/consumers/__init__.py
kal_utils/event_messaging/consumers/base.py
kal_utils/event_messaging/consumers/kafka.py
kal_utils/event_messaging/consumers/kafka_async.py
kal_utils/event_messaging/consumers/pubsub.py
kal_utils/event_messaging/consumers/pubsub_async.py
kal_utils/event_messaging/consumers/rabbitmq.py
kal_utils/event_messaging/consumers/rabbitmq_async.py
kal_utils/event_messaging/core/__init__.py
kal_utils/event_messaging/core/constants.py
kal_utils/event_messaging/core/logging.py
kal_utils/event_messaging/core/rmq_consumer_process.py
kal_utils/event_messaging/core/schema.py
kal_utils/event_messaging/core/settings.py
kal_utils/event_messaging/core/utils/__init__.py
kal_utils/event_messaging/core/utils/connection_manager.py
kal_utils/event_messaging/core/utils/handlers.py
kal_utils/event_messaging/core/utils/topic_message_example.py
kal_utils/event_messaging/producers/__init__.py
kal_utils/event_messaging/producers/base.py
kal_utils/event_messaging/producers/kafka.py
kal_utils/event_messaging/producers/kafka_async.py
kal_utils/event_messaging/producers/pubsub.py
kal_utils/event_messaging/producers/pubsub_async.py
kal_utils/event_messaging/producers/rabbitmq.py
kal_utils/event_messaging/producers/rabbitmq_async.py
kal_utils/event_messaging/retrievers/__init__.py
kal_utils/event_messaging/retrievers/consumer/__init__.py
kal_utils/event_messaging/retrievers/consumer/async_retriever.py
kal_utils/event_messaging/retrievers/consumer/base_consumer_retriever.py
kal_utils/event_messaging/retrievers/consumer/retriever.py
kal_utils/event_messaging/retrievers/producer/__init__.py
kal_utils/event_messaging/retrievers/producer/async_retriever.py
kal_utils/event_messaging/retrievers/producer/base_producer_retriever.py
kal_utils-2.0.8.44.dist-info/LICENSE
kal_utils-2.0.8.44.dist-info/METADATA
kal_utils-2.0.8.44.dist-info/WHEEL
kal_utils-2.0.8.44.dist-info/entry_points.txt
kal_utils-2.0.8.44.dist-info/top_level.txt
kal_utils-2.0.8.44.dist-info/RECORD
