Metadata-Version: 2.2
Name: kal_utils
Version: 2.0.8.44
Summary: Kaleidoo utils package
Home-page: https://github.com/kaleidoo-ai/Kal-Utils
Author: Bar Horovitz
Author-email: Bar Lander <barh@kaleidoo.ai>
License: MIT License
Project-URL: Homepage, https://github.com/BarLanderK/kal-utils
Keywords: kal-utils
Classifier: Intended Audience :: Developers
Classifier: License :: OSI Approved :: MIT License
Classifier: Natural Language :: English
Classifier: Programming Language :: Python :: 3.8
Classifier: Programming Language :: Python :: 3.9
Classifier: Programming Language :: Python :: 3.10
Classifier: Programming Language :: Python :: 3.11
Classifier: Programming Language :: Python :: 3.12
Requires-Python: >=3.7
License-File: LICENSE
Requires-Dist: httpx
Requires-Dist: fastapi
Requires-Dist: mongoengine
Requires-Dist: pymongo
Requires-Dist: google-cloud-storage==2.18.2
Requires-Dist: google-cloud-pubsub==2.20.0
Requires-Dist: pytz
Requires-Dist: pydantic
Requires-Dist: minio==7.2.8
Requires-Dist: tqdm
Requires-Dist: boto3==1.35.39
Requires-Dist: tempo==0.12
Requires-Dist: opentelemetry-api==1.27.0
Requires-Dist: opentelemetry-sdk==1.27.0
Requires-Dist: opentelemetry-exporter-jaeger==1.21.0
Requires-Dist: opentelemetry-exporter-otlp==1.27.0
Requires-Dist: botocore==1.35.39
Requires-Dist: prometheus_client==0.21.1
Requires-Dist: psutil
Requires-Dist: aio-pika
Requires-Dist: aiokafka
Requires-Dist: loguru==0.7.3
Requires-Dist: requests==2.32.3
Requires-Dist: opentelemetry.instrumentation.logging==0.48b0
Requires-Dist: opentelemetry.instrumentation.httpx==0.48b0
Requires-Dist: opentelemetry.instrumentation.requests==0.48b0
Requires-Dist: opentelemetry-instrumentation-fastapi==0.48b0
Requires-Dist: starlette==0.40.0
Requires-Dist: kafka-python==2.0.2
Requires-Dist: pika
Requires-Dist: python-dotenv
Requires-Dist: pydantic-settings
Requires-Dist: tenacity
Provides-Extra: all
Requires-Dist: kal-utils[extra]; extra == "all"
Provides-Extra: extra
Requires-Dist: pandas; extra == "extra"
Dynamic: author
Dynamic: home-page
Dynamic: requires-python
